odoo/addons/account_payment_mode/README.rst
odoo/addons/account_payment_mode/__init__.py
odoo/addons/account_payment_mode/__manifest__.py
odoo/addons/account_payment_mode/hooks.py
odoo/addons/account_payment_mode/demo/partner_demo.xml
odoo/addons/account_payment_mode/demo/payment_demo.xml
odoo/addons/account_payment_mode/i18n/account_payment_mode.pot
odoo/addons/account_payment_mode/i18n/am.po
odoo/addons/account_payment_mode/i18n/ca.po
odoo/addons/account_payment_mode/i18n/da_DK.po
odoo/addons/account_payment_mode/i18n/de.po
odoo/addons/account_payment_mode/i18n/el_GR.po
odoo/addons/account_payment_mode/i18n/es.po
odoo/addons/account_payment_mode/i18n/es_AR.po
odoo/addons/account_payment_mode/i18n/es_CL.po
odoo/addons/account_payment_mode/i18n/es_ES.po
odoo/addons/account_payment_mode/i18n/fi.po
odoo/addons/account_payment_mode/i18n/fr.po
odoo/addons/account_payment_mode/i18n/fr_FR.po
odoo/addons/account_payment_mode/i18n/gl.po
odoo/addons/account_payment_mode/i18n/hr.po
odoo/addons/account_payment_mode/i18n/it.po
odoo/addons/account_payment_mode/i18n/nb_NO.po
odoo/addons/account_payment_mode/i18n/nl.po
odoo/addons/account_payment_mode/i18n/pt.po
odoo/addons/account_payment_mode/i18n/pt_BR.po
odoo/addons/account_payment_mode/i18n/pt_PT.po
odoo/addons/account_payment_mode/i18n/sl.po
odoo/addons/account_payment_mode/i18n/sv.po
odoo/addons/account_payment_mode/i18n/sv_SE.po
odoo/addons/account_payment_mode/i18n/tr.po
odoo/addons/account_payment_mode/i18n/zh_CN.po
odoo/addons/account_payment_mode/models/__init__.py
odoo/addons/account_payment_mode/models/account_journal.py
odoo/addons/account_payment_mode/models/account_move.py
odoo/addons/account_payment_mode/models/account_move_line.py
odoo/addons/account_payment_mode/models/account_payment_method.py
odoo/addons/account_payment_mode/models/account_payment_mode.py
odoo/addons/account_payment_mode/models/res_partner.py
odoo/addons/account_payment_mode/readme/CONFIGURE.md
odoo_addon_account_payment_mode-19.0.1.0.0.2.dist-info/METADATA
odoo_addon_account_payment_mode-19.0.1.0.0.2.dist-info/WHEEL
odoo_addon_account_payment_mode-19.0.1.0.0.2.dist-info/top_level.txt
odoo_addon_account_payment_mode-19.0.1.0.0.2.dist-info/RECORD
